mecher_bs_api_client/__init__.py
mecher_bs_api_client/browserstack_api_init.py
mecher_bs_api_client/utils.py
mecher_bs_api_client/blocks/__init__.py
mecher_bs_api_client/blocks/artefact_blocks.py
mecher_bs_api_client/blocks/blocks_aggregator/__init__.py
mecher_bs_api_client/blocks/blocks_aggregator/_blocks.py
mecher_bs_api_client/blocks/blocks_aggregator/blocks.py
mecher_bs_api_client/endpoints/__init__.py
mecher_bs_api_client/endpoints/browserstack_api.py
mecher_bs_api_client/endpoints/app_automate/__init__.py
mecher_bs_api_client/endpoints/app_automate/app_automate.py
mecher_bs_api_client-0.0.23.dist-info/METADATA
mecher_bs_api_client-0.0.23.dist-info/WHEEL
mecher_bs_api_client-0.0.23.dist-info/top_level.txt
mecher_bs_api_client-0.0.23.dist-info/RECORD
